kicost/AUTHORS.rst
kicost/HISTORY.rst
kicost/__init__.py
kicost/__main__.py
kicost/ansi.py
kicost/config.py
kicost/global_vars.py
kicost/kicad_config.py
kicost/kicost.ico
kicost/kicost.py
kicost/kicost_config.py
kicost/kicost_gui.py
kicost/kicost_kicadplugin.py
kicost/kitspace.png
kicost/log.py
kicost/log__.py
kicost/os_windows.py
kicost/sexpdata.py
kicost/spreadsheet.py
kicost/version.py
kicost/currency_converter/__init__.py
kicost/currency_converter/currency_converter.py
kicost/currency_converter/currency_tables.py
kicost/currency_converter/default_rates.py
kicost/currency_converter/download_rates.py
kicost/distributors/__init__.py
kicost/distributors/api_digikey.py
kicost/distributors/api_element14.py
kicost/distributors/api_mouser.py
kicost/distributors/api_nexar.py
kicost/distributors/api_partinfo_kitspace.py
kicost/distributors/api_tme.py
kicost/distributors/dist_local_template.py
kicost/distributors/distributor.py
kicost/distributors/distributors_info.py
kicost/distributors/global_vars.py
kicost/distributors/log__.py
kicost/edas/__init__.py
kicost/edas/eda.py
kicost/edas/eda_altium.py
kicost/edas/eda_kicad.py
kicost/edas/generic_csv.py
kicost/edas/log__.py
kicost/edas/tools.py
tests/__init__.py
tests/dummy-web-server.py
tests/test_kicost.py
kicost-1.1.20.dist-info/LICENSE
kicost-1.1.20.dist-info/METADATA
kicost-1.1.20.dist-info/WHEEL
kicost-1.1.20.dist-info/entry_points.txt
kicost-1.1.20.dist-info/top_level.txt
kicost-1.1.20.dist-info/RECORD
