Metadata-Version: 2.1
Name: kicost
Version: 1.1.20
Summary: Build cost spreadsheet for a KiCad project.
Home-page: https://hildogjr.github.io/KiCost
Author: XESS Corporation
Author-email: info@xess.com
License: MIT
Project-URL: Doc, https://hildogjr.github.io/KiCost
Project-URL: Git, https://github.com/hildogjr/KiCost
Keywords: KiCAD,BOM,electronics
Platform: UNKNOWN
Classifier: Development Status :: 4 - Beta
Classifier: Intended Audience :: Developers
Classifier: License :: OSI Approved :: MIT License
Classifier: Natural Language :: English
Classifier: Programming Language :: Python :: 2.7
Classifier: Programming Language :: Python :: 3.5
Classifier: Programming Language :: Python :: 3.7
Classifier: Programming Language :: Python :: 3.8
Classifier: Programming Language :: Python :: 3.9
Classifier: Programming Language :: Python :: Implementation :: CPython
Classifier: Programming Language :: Python :: Implementation :: PyPy
Requires-Dist: XlsxWriter (>=0.7.3)
Requires-Dist: beautifulsoup4 (>=4.3.2)
Requires-Dist: colorama
Requires-Dist: kicost-digikey-api-v3
Requires-Dist: kicost-digikey-api-v4
Requires-Dist: lxml (>=3.7.2)
Requires-Dist: pyyaml
Requires-Dist: requests (>=2.18.4)
Requires-Dist: tqdm (>=4.30.0)
Requires-Dist: validators (>=0.14.2)
Requires-Dist: wxPython (>=3.0.2)
